CHANGES
LICENSE
MANIFEST.in
README
setup.cfg
setup.py
sphinxcontrib/__init__.py
sphinxcontrib/clearquest/__init__.py
sphinxcontrib/clearquest/connection.py
sphinxcontrib/clearquest/directive.py
sphinxcontrib_clearquest.egg-info/PKG-INFO
sphinxcontrib_clearquest.egg-info/SOURCES.txt
sphinxcontrib_clearquest.egg-info/dependency_links.txt
sphinxcontrib_clearquest.egg-info/namespace_packages.txt
sphinxcontrib_clearquest.egg-info/requires.txt
sphinxcontrib_clearquest.egg-info/top_level.txt
sphinxcontrib_clearquest.egg-info/zip-safe