Metadata-Version: 1.0
Name: sphinxcontrib-clearquest
Version: 0.6
Summary: Sphinx "clearquest" extension
Home-page: http://bitbucket.org/birkenfeld/sphinx-contrib
Author: Robin Jarry
Author-email: robin.jarry@gmail.com
License: BSD
Download-URL: http://pypi.python.org/pypi/sphinxcontrib-clearquest
Keywords: clearquest,sphinx
Platform: Windows
Classifier: Development Status :: 4 - Beta
Classifier: Environment :: Console
Classifier: Environment :: Win32 (MS Windows)
Classifier: Intended Audience :: Developers
Classifier: License :: OSI Approved :: BSD License
Classifier: Operating System :: Microsoft :: Windows
Classifier: Programming Language :: Python
Classifier: Topic :: Documentation
Classifier: Topic :: Utilities
